s3_manager/__init__.py
s3_manager/s3_manager.py
modelmgr-0.1.0.dist-info/METADATA
modelmgr-0.1.0.dist-info/WHEEL
modelmgr-0.1.0.dist-info/top_level.txt
modelmgr-0.1.0.dist-info/RECORD
